hmmkay/__init__.py
hmmkay/_utils.py
hmmkay/hmm.py
hmmkay/utils.py
hmmkay-0.0.1.dist-info/LICENSE.txt
hmmkay-0.0.1.dist-info/METADATA
hmmkay-0.0.1.dist-info/WHEEL
hmmkay-0.0.1.dist-info/top_level.txt
hmmkay-0.0.1.dist-info/RECORD
