Metadata-Version: 2.1
Name: hmmkay
Version: 0.0.1
Summary: Discrete Hidden Markov Models with Numba
Home-page: https://github.com/NicolasHug/hmmkay/
Author: Nicolas Hug
Author-email: contact@nicolas-hug.com
License: MIT
Platform: any
Classifier: Development Status :: 3 - Alpha
Classifier: Environment :: Console
Classifier: Intended Audience :: Developers
Classifier: Intended Audience :: Science/Research
Classifier: License :: OSI Approved :: MIT License
Classifier: Operating System :: OS Independent
Classifier: Programming Language :: Python :: 3.6
Classifier: Programming Language :: Python :: 3.7
Classifier: Topic :: Scientific/Engineering
Requires-Python: >=3.6
Requires-Dist: numpy
Requires-Dist: numba
